beancount_chase/__init__.py
beancount_chase/checking.py
beancount_chase/checking_test.py
beancount_chase/credit.py
beancount_chase/credit_test.py
beancount_chase_bank-0.2.15.dist-info/LICENSE
beancount_chase_bank-0.2.15.dist-info/METADATA
beancount_chase_bank-0.2.15.dist-info/WHEEL
beancount_chase_bank-0.2.15.dist-info/top_level.txt
beancount_chase_bank-0.2.15.dist-info/RECORD
