Metadata-Version: 2.1
Name: beancount-chase-bank
Version: 0.2.15
Summary: Import Chase banking transactions into beancount format
Home-page: https://github.com/mtlynch/beancount-chase.git
Author: Michael Lynch
License: MIT
Keywords: chase beancount bookkeeping finance
Requires-Python: >=3.9
License-File: LICENSE
Requires-Dist: beancount==2.3.6
Requires-Dist: titlecase==2.4.1
